natsulang/__init__.py
natsulang-1.0.0b11.dist-info/LICENSE
natsulang-1.0.0b11.dist-info/METADATA
natsulang-1.0.0b11.dist-info/WHEEL
natsulang-1.0.0b11.dist-info/entry_points.txt
natsulang-1.0.0b11.dist-info/top_level.txt
natsulang-1.0.0b11.dist-info/RECORD
