Metadata-Version: 2.1
Name: natsulang
Version: 1.0.0b11
Summary: A text-processing language based on Python 3.
Home-page: https://github.com/CJC-Apps/natsulang
Author: CJC Apps
Author-email: jrgdcharlieyan@gmail.com
License: UNKNOWN
Platform: UNKNOWN
Classifier: Programming Language :: Python :: 3
Classifier: License :: OSI Approved :: MIT License
Classifier: Operating System :: OS Independent
Requires-Python: >=3.0
